lytekitplugins_pods-0.7.4-py3.10-nspkg.pth
flytekitplugins/pod/__init__.py
flytekitplugins/pod/task.py
lytekitplugins_pods-0.7.4.dist-info/LICENSE
lytekitplugins_pods-0.7.4.dist-info/METADATA
lytekitplugins_pods-0.7.4.dist-info/WHEEL
lytekitplugins_pods-0.7.4.dist-info/namespace_packages.txt
lytekitplugins_pods-0.7.4.dist-info/top_level.txt
lytekitplugins_pods-0.7.4.dist-info/RECORD
